Flask_RESTful-0.3.7.dist-info/DESCRIPTION.rst
Flask_RESTful-0.3.7.dist-info/METADATA
Flask_RESTful-0.3.7.dist-info/RECORD
Flask_RESTful-0.3.7.dist-info/WHEEL
Flask_RESTful-0.3.7.dist-info/metadata.json
Flask_RESTful-0.3.7.dist-info/top_level.txt
flask_restful/__init__.py
flask_restful/__version__.py
flask_restful/fields.py
flask_restful/inputs.py
flask_restful/reqparse.py
flask_restful/representations/__init__.py
flask_restful/representations/json.py
flask_restful/utils/__init__.py
flask_restful/utils/cors.py
flask_restful/utils/crypto.py
