Metadata-Version: 2.1
Name: Flask-RESTful
Version: 0.3.7
Summary: Simple framework for creating REST APIs
Home-page: https://www.github.com/flask-restful/flask-restful/
Author: Twilio API Team
Author-email: help@twilio.com
License: BSD
Platform: any
Classifier: Framework :: Flask
Classifier: Programming Language :: Python :: 2
Classifier: Programming Language :: Python :: 2.7
Classifier: Programming Language :: Python :: 3
Classifier: Programming Language :: Python :: 3.4
Classifier: Programming Language :: Python :: 3.5
Classifier: Programming Language :: Python :: 3.6
Classifier: Programming Language :: Python :: 3.7
Classifier: License :: OSI Approved :: BSD License
Provides-Extra: docs
